README.md
setup.py
sabersql/MySQLConnection.py
sabersql/PDownloader.py
sabersql/PImporter.py
sabersql/ProgressHandler.py
sabersql/RDownloader.py
sabersql/RImporter.py
sabersql/SDownloader.py
sabersql/SImporter.py
sabersql/Schemas.py
sabersql/Utilities.py
sabersql/__init__.py
sabersql/__main__.py
sabersql.egg-info/PKG-INFO
sabersql.egg-info/SOURCES.txt
sabersql.egg-info/dependency_links.txt
sabersql.egg-info/entry_points.txt
sabersql.egg-info/requires.txt
sabersql.egg-info/top_level.txt