Metadata-Version: 2.1
Name: sabersql
Version: 1.1.1
Summary: SaberSQL is a tool to scrape baseball data from various sources and import it into a MySQL database.
Home-page: https://github.com/liam923/sabersql
Author: William Stevenson
Author-email: stevenson.w@husky.neu.edu
License: UNKNOWN
Download-URL: https://github.com/liam923/sabersql/archive/v1.1.1.tar.gz
Platform: UNKNOWN
Classifier: Programming Language :: Python :: 3
Classifier: License :: OSI Approved :: MIT License
Classifier: Operating System :: OS Independent
